plykit/__init__.py
plykit/plugin_base.py
plykit/plugins/__init__.py
plykit/plugins/center_plugin.py
plykit/plugins/downsample_plugin.py
plykit/plugins/export_combined_ply.py
plykit/plugins/filter_z_plugin.py
plykit/plugins/ground_plugin.py
plykit/plugins/rotate_plugin.py
plykit/plugins/save_txt_plugin.py
plykit/plugins/scale_plugin.py
plykit/plugins/sh3_to_streetgs_plugin.py
plykit/plugins/stats_plugin.py
plykit/plugins/trellis_to_streetgs_plugin.py
plykit/plykit_global.py
plykit/plykit_gui.py
plykit-0.1.1.dist-info/METADATA
plykit-0.1.1.dist-info/WHEEL
plykit-0.1.1.dist-info/entry_points.txt
plykit-0.1.1.dist-info/RECORD
